Noema/BaseGenerator.py
Noema/Generator.py
Noema/Subject.py
Noema/__init__.py
Noema/atomic_types.py
Noema/cfg.py
Noema/code_gen.py
Noema/composed_types.py
Noema/information.py
Noema/noesis_wrapper.py
Noema/programming_langugages.py
Noema/reset.py
Noema/selectors.py
Noema/semPy.py
Noema/substring.py
Noema/text_gen.py
tests/__init__.py
tests/test_noema.py
Noema-1.1.3.dist-info/LICENSE
Noema-1.1.3.dist-info/METADATA
Noema-1.1.3.dist-info/WHEEL
Noema-1.1.3.dist-info/top_level.txt
Noema-1.1.3.dist-info/RECORD
