Metadata-Version: 2.1
Name: Noema
Version: 1.1.3
Summary: A declarative way to control LLMs.
Home-page: https://github.com/AlbanPerli/Noema-Declarative-AI
Author: Alban Perli
Author-email: alban.perli@gmail.com
Classifier: Programming Language :: Python :: 3
Classifier: License :: OSI Approved :: Apache Software License
Classifier: Operating System :: OS Independent
Requires-Python: >=3.8
License-File: LICENSE
Requires-Dist: guidance==0.1.15
Requires-Dist: varname
